[
     { 
          "id": 0,
          "title": "Projeto de Integração Numérica",
          "description": "Lorem Ipsum is simply dummy text of the printing and  typesetting industry. Lorem Ipsum has been the industry's standard dummy text ever since the 1500s.",
          "image1": "Assembly.png"
     },
     { 
          "id": 1,
          "title": "Projeto de Integração Numérica 2",
          "description": "Lorem Ipsum is simply dummy text of the printing and  typesetting industry. Lorem Ipsum has been the industry's standard dummy text ever since the 1500s.",
          "image1": "Nissan.png"
     },
     { 
          "id": 2,
          "title": "Projeto de Integração Numérica 2",
          "description": "Lorem Ipsum is simply dummy text of the printing and  typesetting industry. Lorem Ipsum has been the industry's standard dummy text ever since the 1500s.",
          "image1": "Banheira1.png"
     }
] 